caching_secrets_manager_backend/__init__.py
caching_secrets_manager_backend/caching_secrets_manager_backend.py
airflow_caching_google_secret_manager_backend-1.0.4.dist-info/LICENSE
airflow_caching_google_secret_manager_backend-1.0.4.dist-info/METADATA
airflow_caching_google_secret_manager_backend-1.0.4.dist-info/WHEEL
airflow_caching_google_secret_manager_backend-1.0.4.dist-info/top_level.txt
airflow_caching_google_secret_manager_backend-1.0.4.dist-info/RECORD
