Metadata-Version: 2.1
Name: airflow-caching-google-secret-manager-backend
Version: 1.0.4
Summary: Use Google Secret Manager with environment variable fallback and caching.
Author: Lukas Rieder
Author-email: Lukas Rieder <lukas@harren.com>
License: MIT License
Project-URL: Homepage, https://github.com/puc-business-intelligence/airflow-caching-secret-manager-backend
Keywords: google,google-secret-manager,airflow
Classifier: License :: OSI Approved :: MIT License
Classifier: Programming Language :: Python
Classifier: Programming Language :: Python :: 3
Requires-Python: >=3.8
License-File: LICENSE
Requires-Dist: google-cloud-secret-manager
